{
  "id": "royd00146",
  "title": "兄嫁とキスだけの関係…のはずが互いに我慢できずに唾液を濃厚に絡ませ、何度も何度も隠れて種付け性交を繰り返した。 五日市芽依",
  "review": "<h2>【SEO特化レビュー】『兄嫁とキスだけの関係…のはずが互いに我慢できずに唾液を濃厚に絡ませ、何度も何度も隠れて種付け性交を繰り返した。 五日市芽依』が選ばれる理由と作品の全貌</h2>\n<p>今期最も注目を集めているタイトルの一つ、<strong>『兄嫁とキスだけの関係…のはずが互いに我慢できずに唾液を濃厚に絡ませ、何度も何度も隠れて種付け性交を繰り返した。 五日市芽依』</strong>。トップレーベルロイヤルと名女優【五日市芽依】のタッグが実現した、まさに奇跡のような一本です。</p>\n<h2>本作が提示する新しい楽しみ方</h2>\n<ol style='padding-left: 20px; margin: 16px 0;'>\n<li style='margin-bottom: 8px;'>五日市芽依の息遣いまで感じられる圧倒的な至近距離カット。</li>\n<li style='margin-bottom: 8px;'>ハイビジョン、独占配信、寝取り・寝取られ・NTR、人妻・主婦好きには堪らない洗練された演出美。</li>\n</ol>\n<h2>結論：今すぐ見るべき理由</h2>\n<p>『兄嫁とキスだけの関係…のはずが互いに我慢できずに唾液を濃厚に絡ませ、何度も何度も隠れて種付け性交を繰り返した。 五日市芽依』は期待以上のクオリティと感動を届けてくれる間違いのない作品です。</p>\n<h2>まとめ：『兄嫁とキスだけの関係…のはずが互いに我慢できずに唾液を濃厚に絡ませ、何度も何度も隠れて種付け性交を繰り返した。 五日市芽依』の配信を今すぐチェック</h2>\n<p>ぜひ公式配信ページで、その目でお確かめください！</p>",
  "image": "https://pics.dmm.co.jp/digital/video/royd00146/royd00146pl.jpg",
  "sample_images": [
    "https://pics.dmm.co.jp/digital/video/royd00146/royd00146jp-1.jpg",
    "https://pics.dmm.co.jp/digital/video/royd00146/royd00146jp-2.jpg",
    "https://pics.dmm.co.jp/digital/video/royd00146/royd00146jp-3.jpg",
    "https://pics.dmm.co.jp/digital/video/royd00146/royd00146jp-4.jpg",
    "https://pics.dmm.co.jp/digital/video/royd00146/royd00146jp-5.jpg"
  ],
  "affiliate_url": "https://al.fanza.co.jp/?lurl=https%3A%2F%2Fvideo.dmm.co.jp%2Fav%2Fcontent%2F%3Fid%3Droyd00146&af_id=onchan555-999&ch=api",
  "genres": [
    "ハイビジョン",
    "独占配信",
    "寝取り・寝取られ・NTR",
    "人妻・主婦",
    "中出し",
    "単体作品",
    "巨乳",
    "キス・接吻"
  ],
  "actresses": [
    "五日市芽依"
  ],
  "maker": "ロイヤル",
  "date": "2026-06-28",
  "labels": [
    "ハイビジョン",
    "中出し",
    "独占配信",
    "寝取り・寝取られ・NTR",
    "人妻・主婦",
    "五日市芽依",
    "ロイヤル"
  ]
}